[{"type": "Lever", "pos": [7, 5], "level": 0, "out": false, "connections": [], "inputs": [], "is_connected": []}, {"type": "Lever", "pos": [11, 7], "level": 0, "out": false, "connections": [[{"pos": [13, 7], "level": 0}, 0]], "inputs": [], "is_connected": []}, {"type": "Lever", "pos": [11, 5], "level": 0, "out": false, "connections": [[{"pos": [13, 5], "level": 0}, 0]], "inputs": [], "is_connected": []}, {"type": "Not", "pos": [13, 7], "level": 0, "out": true, "connections": [[{"pos": [15, 6], "level": 0}, 1], [{"pos": [18, 7], "level": 0}, 0]], "inputs": [false], "is_connected": [[true, {"pos": [11, 7], "level": 0}, 0]]}, {"type": "Not", "pos": [13, 5], "level": 0, "out": true, "connections": [[{"pos": [15, 6], "level": 0}, 0], [{"pos": [18, 5], "level": 0}, 1]], "inputs": [false], "is_connected": [[true, {"pos": [11, 5], "level": 0}, 0]]}, {"type": "OR", "pos": [15, 6], "level": 0, "out": true, "connections": [[{"pos": [17, 6], "level": 0}, 0]], "inputs": [true, true, false], "is_connected": [[true, {"pos": [13, 5], "level": 0}, 0], [true, {"pos": [13, 7], "level": 0}, 1], [false]]}, {"type": "Not", "pos": [17, 6], "level": 0, "out": false, "connections": [[{"pos": [18, 7], "level": 0}, 1], [{"pos": [18, 5], "level": 0}, 0]], "inputs": [true], "is_connected": [[true, {"pos": [15, 6], "level": 0}, 0]]}, {"type": "OR", "pos": [18, 7], "level": 0, "out": true, "connections": [[{"pos": [20, 7], "level": 0}, 0]], "inputs": [true, false, false], "is_connected": [[true, {"pos": [13, 7], "level": 0}, 0], [true, {"pos": [17, 6], "level": 0}, 1], [false]]}, {"type": "OR", "pos": [18, 5], "level": 0, "out": true, "connections": [[{"pos": [20, 5], "level": 0}, 0]], "inputs": [false, true, false], "is_connected": [[true, {"pos": [17, 6], "level": 0}, 0], [true, {"pos": [13, 5], "level": 0}, 1], [false]]}, {"type": "Not", "pos": [20, 5], "level": 0, "out": false, "connections": [[{"pos": [22, 6], "level": 0}, 0]], "inputs": [true], "is_connected": [[true, {"pos": [18, 5], "level": 0}, 0]]}, {"type": "Not", "pos": [20, 7], "level": 0, "out": false, "connections": [[{"pos": [22, 6], "level": 0}, 1]], "inputs": [true], "is_connected": [[true, {"pos": [18, 7], "level": 0}, 0]]}, {"type": "OR", "pos": [22, 6], "level": 0, "out": false, "connections": [], "inputs": [false, false, false], "is_connected": [[true, {"pos": [20, 5], "level": 0}, 0], [true, {"pos": [20, 7], "level": 0}, 1], [false]]}, {"type": "Not", "pos": [13, 9], "level": 0, "out": true, "connections": [[{"pos": [13, 10], "level": 0}, 0], [{"pos": [14, 9], "level": 0}, 0]], "inputs": [false], "is_connected": [[true, {"pos": [11, 9], "level": 0}, 0]]}, {"type": "Not", "pos": [13, 11], "level": 0, "out": true, "connections": [[{"pos": [13, 10], "level": 0}, 1], [{"pos": [14, 11], "level": 0}, 0]], "inputs": [false], "is_connected": [[true, {"pos": [10, 11], "level": 0}, 0]]}, {"type": "OR", "pos": [13, 10], "level": 0, "out": true, "connections": [[{"pos": [14, 10], "level": 0}, 0]], "inputs": [true, true, false], "is_connected": [[true, {"pos": [13, 9], "level": 0}, 0], [true, {"pos": [13, 11], "level": 0}, 1], [false]]}, {"type": "Not", "pos": [14, 10], "level": 0, "out": false, "connections": [[{"pos": [14, 11], "level": 0}, 1], [{"pos": [14, 9], "level": 0}, 1], [{"pos": [18, 12], "level": 0}, 0]], "inputs": [true], "is_connected": [[true, {"pos": [13, 10], "level": 0}, 0]]}, {"type": "OR", "pos": [14, 11], "level": 0, "out": true, "connections": [[{"pos": [15, 11], "level": 0}, 0]], "inputs": [true, false, false], "is_connected": [[true, {"pos": [13, 11], "level": 0}, 0], [true, {"pos": [14, 10], "level": 0}, 1], [false]]}, {"type": "OR", "pos": [14, 9], "level": 0, "out": true, "connections": [[{"pos": [15, 9], "level": 0}, 0]], "inputs": [true, false, false], "is_connected": [[true, {"pos": [13, 9], "level": 0}, 0], [true, {"pos": [14, 10], "level": 0}, 1], [false]]}, {"type": "Not", "pos": [15, 11], "level": 0, "out": false, "connections": [[{"pos": [15, 10], "level": 0}, 1]], "inputs": [true], "is_connected": [[true, {"pos": [14, 11], "level": 0}, 0]]}, {"type": "Not", "pos": [15, 9], "level": 0, "out": false, "connections": [[{"pos": [15, 10], "level": 0}, 0]], "inputs": [true], "is_connected": [[true, {"pos": [14, 9], "level": 0}, 0]]}, {"type": "OR", "pos": [15, 10], "level": 0, "out": false, "connections": [[{"pos": [19, 9], "level": 0}, 0]], "inputs": [false, false, false], "is_connected": [[true, {"pos": [15, 9], "level": 0}, 0], [true, {"pos": [15, 11], "level": 0}, 1], [false]]}, {"type": "Lever", "pos": [11, 9], "level": 0, "out": false, "connections": [[{"pos": [13, 9], "level": 0}, 0]], "inputs": [], "is_connected": []}, {"type": "Lever", "pos": [10, 11], "level": 0, "out": false, "connections": [[{"pos": [13, 11], "level": 0}, 0]], "inputs": [], "is_connected": []}, {"type": "OR", "pos": [19, 9], "level": 0, "out": false, "connections": [], "inputs": [false, false, false], "is_connected": [[true, {"pos": [15, 10], "level": 0}, 0], [false], [false]]}, {"type": "Lever", "pos": [11, 13], "level": 0, "out": false, "connections": [[{"pos": [14, 13], "level": 0}, 0]], "inputs": [], "is_connected": []}, {"type": "Lever", "pos": [10, 15], "level": 0, "out": false, "connections": [[{"pos": [14, 15], "level": 0}, 0]], "inputs": [], "is_connected": []}, {"type": "Not", "pos": [14, 13], "level": 0, "out": true, "connections": [[{"pos": [14, 14], "level": 0}, 1], [{"pos": [15, 13], "level": 0}, 0]], "inputs": [false], "is_connected": [[true, {"pos": [11, 13], "level": 0}, 0]]}, {"type": "Not", "pos": [14, 15], "level": 0, "out": true, "connections": [[{"pos": [14, 14], "level": 0}, 0], [{"pos": [15, 15], "level": 0}, 0]], "inputs": [false], "is_connected": [[true, {"pos": [10, 15], "level": 0}, 0]]}, {"type": "Not", "pos": [16, 13], "level": 0, "out": false, "connections": [[{"pos": [16, 14], "level": 0}, 0]], "inputs": [true], "is_connected": [[true, {"pos": [15, 13], "level": 0}, 0]]}, {"type": "Not", "pos": [16, 15], "level": 0, "out": false, "connections": [[{"pos": [16, 14], "level": 0}, 1]], "inputs": [true], "is_connected": [[true, {"pos": [15, 15], "level": 0}, 0]]}, {"type": "Not", "pos": [15, 14], "level": 0, "out": false, "connections": [[{"pos": [15, 13], "level": 0}, 1], [{"pos": [15, 15], "level": 0}, 1]], "inputs": [true], "is_connected": [[true, {"pos": [14, 14], "level": 0}, 0]]}, {"type": "OR", "pos": [14, 14], "level": 0, "out": true, "connections": [[{"pos": [15, 14], "level": 0}, 0]], "inputs": [true, true, false], "is_connected": [[true, {"pos": [14, 15], "level": 0}, 0], [true, {"pos": [14, 13], "level": 0}, 1], [false]]}, {"type": "OR", "pos": [15, 15], "level": 0, "out": true, "connections": [[{"pos": [16, 15], "level": 0}, 0]], "inputs": [true, false, false], "is_connected": [[true, {"pos": [14, 15], "level": 0}, 0], [true, {"pos": [15, 14], "level": 0}, 1], [false]]}, {"type": "OR", "pos": [16, 14], "level": 0, "out": false, "connections": [[{"pos": [18, 14], "level": 0}, 0]], "inputs": [false, false, false], "is_connected": [[true, {"pos": [16, 13], "level": 0}, 0], [true, {"pos": [16, 15], "level": 0}, 1], [false]]}, {"type": "OR", "pos": [15, 13], "level": 0, "out": true, "connections": [[{"pos": [16, 13], "level": 0}, 0]], "inputs": [true, false, false], "is_connected": [[true, {"pos": [14, 13], "level": 0}, 0], [true, {"pos": [15, 14], "level": 0}, 1], [false]]}, {"type": "Not", "pos": [18, 12], "level": 0, "out": true, "connections": [[{"pos": [19, 12], "level": 0}, 0], [{"pos": [18, 13], "level": 0}, 0]], "inputs": [false], "is_connected": [[true, {"pos": [14, 10], "level": 0}, 0]]}, {"type": "Not", "pos": [18, 14], "level": 0, "out": true, "connections": [[{"pos": [19, 14], "level": 0}, 0], [{"pos": [18, 13], "level": 0}, 1]], "inputs": [false], "is_connected": [[true, {"pos": [16, 14], "level": 0}, 0]]}, {"type": "Not", "pos": [19, 13], "level": 0, "out": false, "connections": [[{"pos": [19, 12], "level": 0}, 1], [{"pos": [19, 14], "level": 0}, 1]], "inputs": [true], "is_connected": [[true, {"pos": [18, 13], "level": 0}, 0]]}, {"type": "Not", "pos": [20, 12], "level": 0, "out": false, "connections": [[{"pos": [20, 13], "level": 0}, 0]], "inputs": [true], "is_connected": [[true, {"pos": [19, 12], "level": 0}, 0]]}, {"type": "Not", "pos": [20, 14], "level": 0, "out": false, "connections": [[{"pos": [20, 13], "level": 0}, 1]], "inputs": [true], "is_connected": [[true, {"pos": [19, 14], "level": 0}, 0]]}, {"type": "OR", "pos": [18, 13], "level": 0, "out": true, "connections": [[{"pos": [19, 13], "level": 0}, 0]], "inputs": [true, true, false], "is_connected": [[true, {"pos": [18, 12], "level": 0}, 0], [true, {"pos": [18, 14], "level": 0}, 1], [false]]}, {"type": "OR", "pos": [19, 14], "level": 0, "out": true, "connections": [[{"pos": [20, 14], "level": 0}, 0]], "inputs": [true, false, false], "is_connected": [[true, {"pos": [18, 14], "level": 0}, 0], [true, {"pos": [19, 13], "level": 0}, 1], [false]]}, {"type": "OR", "pos": [20, 13], "level": 0, "out": false, "connections": [], "inputs": [false, false, false], "is_connected": [[true, {"pos": [20, 12], "level": 0}, 0], [true, {"pos": [20, 14], "level": 0}, 1], [false]]}, {"type": "OR", "pos": [19, 12], "level": 0, "out": true, "connections": [[{"pos": [20, 12], "level": 0}, 0]], "inputs": [true, false, false], "is_connected": [[true, {"pos": [18, 12], "level": 0}, 0], [true, {"pos": [19, 13], "level": 0}, 1], [false]]}]